plprof/__init__.py
plprof/cli.py
plprof/parse.py
polars_lprof-0.1.1.dist-info/METADATA
polars_lprof-0.1.1.dist-info/WHEEL
polars_lprof-0.1.1.dist-info/entry_points.txt
polars_lprof-0.1.1.dist-info/RECORD
