Metadata-Version: 2.1
Name: polars-lprof
Version: 0.1.1
Summary: Read line profiler reports into Polars DataFrames
Author-Email: Louis Maddox <louismmx@gmail.com>
Requires-Python: >=3.12
Requires-Dist: argh>=0.31.3
Requires-Dist: polars-ls>=0.5.0
Provides-Extra: polars-lts-cpu
Requires-Dist: polars-lts-cpu>=1.21.0; extra == "polars-lts-cpu"
Provides-Extra: polars
Requires-Dist: polars>=1.21.0; extra == "polars"
